{
    "MainCode": {
        "sectionTitle": "human necessities ",
        "classTitle": "agriculture ",
        "subgroupTitle": "automatic devices automatic identification devices for stock ",
        "maingroupTitle": "feeding devices for stock or game takes precedence; for poultry wagons; feeding stacks ",
        "subclass": "K",
        "class": "01",
        "subclassTitle": "animal husbandry care of birds, fishes, insects fishing rearing or breeding animals, not otherwise provided for new breeds of animals ",
        "subgroup": "02",
        "section": "A",
        "maingroup": "5"
    },
    "PatNumber": "08504445",
    "Country": "US",
    "Title": "us-patent-grant"
}